{"package_name":"com.stitcher.app","title":"Stitcher Radio for Podcasts","description":"* 20 Best Apps - TechCrunch \n* 25 Top Android Apps - TIME Magazine \n* Essential Driving App - Wired.com Listen on demand to your favorite news, comedy, sports and talk radio shows and podcasts from sources like NPR, CNN, Fox News, ESPN, This American Life, BBC and more. Stream or download episodes for offline listening. Stitcher also helps you discover interesting things to listen to from over 65,000 shows, based on your listening habits. Change the way you listen to radio - on your schedule, not the schedule of traditional radio.\n\n***FEATURES***\n\n* CREATE CUSTOM STATIONS: \u201cStitch\u201d together your favorite shows in a playlist to create customized stations.\n\n* DISCOVER NEW SHOWS: Stitcher helps you find new shows you\u2019ll love by recommending shows other listeners of the same show also like, as well as personalized show recommendations based on your listening.\n\n* LISTEN ON DEMAND: Get the latest episodes of your favorite shows as soon as they are released, without the hassle of downloading and syncing podcasts. You can also download episodes for offline listening.\n\n* GET BREAKING NEWS: Keep up with the day\u2019s biggest stories on the front page and via breaking news audio alerts sent to your phone.\n\n* SHARE WITH FRIENDS: Share your favorite shows on Twitter, Facebook and email.\n\nStitcher is the best way to stay connected with the information that\u2019s important to you. Stitcher Radio is a smarter way to listen to the radio.\n\n***AWARDS & PRAISE***\n\n- 20 Best Apps - TechCrunch\n- 25 Top Android Apps - TIME Magazine\n- 12 Best Entertainment Apps - PC World\n- Essential Driving App - Wired.com\n- Best News App - Best App Ever Awards\n- Best Mobile News App - Webby's People's Voice Award\n- Top 75 Android Apps - PC Magazine\n- Top 5 Podcast Apps - Mashable\n\n\n\n\n\n\n\n\n\n\n\n\n\n\n\n\n\n\n\n","short_desc":"Stream your favorite radio shows and podcasts on demand","rating":3.9415037631989,"category":"Music & Audio","cat_int":13,"cat_type":0,"cat_key":"MUSIC_AND_AUDIO","cat_keys":["MUSIC_AND_AUDIO","APPLICATION"],"price":"","price_numeric":0,"iap":false,"iap_min":0,"iap_max":0,"downloads":"1,000,000 - 5,000,000","downloads_min":1000000,"downloads_max":5000000,"version":"Varies with device","content_rating":"Everyone","what_is_new":"Stitcher 3.5.8\nPlease contact support@stitcher.com with any questions or feedback!\n","market_update":"2016-06-13T00:00:00+00:00","screenshots":["https:\/\/lh3.googleusercontent.com\/epe6NhULnyo-orYgNWALddQf4Ehk6FF154sS7-hU2VduxyuWUrHfTQe4RvB_YjasxzZn=h310","https:\/\/lh3.googleusercontent.com\/VekRzQ9tmqnjyI8y-1umyUEN5FsMTbnPfVCYbS64Szmo1AtLwrg7yzw-vxhYE8KF=h310","https:\/\/lh3.googleusercontent.com\/Y7iIQ1AHC6eILMgyDwI6OHEbXewqDOV_AQcVyyTtdDru6de1qgZSrGZjmfzNlZm_XA=h310","https:\/\/lh3.googleusercontent.com\/nJWhxcgLQy7Cdc183JNxnyxo-KJaNdgo_UxSPBPVCjzDTjioDbavNXfNl-2l54sy3CU=h310","https:\/\/lh3.googleusercontent.com\/KderqnpZaYkm22qTmBfwFE2TxCpzyx16YSeNZpx5KouSvk20OS70e94dpaeIVTnMjlM=h310","https:\/\/lh3.googleusercontent.com\/sONRA1xLf8SN8Th_PjXhWiVLaUmRMf9tSWsIi9rtICRvpW9rQ10KOqzdSHAcDsb-v6ko=h310","https:\/\/lh3.googleusercontent.com\/3LgEqincPbEzynz1ypkIP-5GOuf20QO2DvN2fvPgoSBWfZ4lYqD2D8DV8_y9OPv7b4mm=h310","https:\/\/lh3.googleusercontent.com\/d9n6UghhIi_u4zdvJljkrVAdFmIbRjBOKao2zb1NsgQWysuoy072q2NnkOOn_4q7lQ=h310","https:\/\/lh4.ggpht.com\/3PTxNaza_AbFoiYiz2sdFw7OPhLb58DLu-ubieG0XKqxjPJA_93jdzHazX8g4pKZ-9yT=h310","https:\/\/lh6.ggpht.com\/D1aW5vC6LTJKAMm-O9MnTyXqbYN4Js2QbviXmzJJCC21bKR2n59MIyM1VjuY0hK8Fow=h310","https:\/\/lh5.ggpht.com\/jhgP3JMGpWNbOPmkFhUJoT7sTYKabLaU2yaZ3YWfKEPdTJ0UYjypfRaiHMQVxjuOKX0=h310","https:\/\/lh3.googleusercontent.com\/imihZczWfzju9s32XTM-mLs5mQtAWP-IXvOESWJU59l3EX6OYEobN23w3F0LhM8AQxFW=h310"],"lang":"en","i18n_lang":["de","ko","pt","zh-tw","pt-br","ja","fr","zh-cn","es"],"price_i18n_countries":[],"website":"http:\/\/stitcher.com","from_developer":[],"badges":["Top Developer"],"created":"2011-11-28T19:13:35+00:00","version_code":115,"developer":"Stitcher, Inc","number_ratings":36979,"icon":"https:\/\/lh3.ggpht.com\/u1O7tcSzw3BbbUtnoNMGtYDcjYaw9ZqMafBeRs6M6G4n1rTVLE1xEdab-JW33RJuWQ=w300","icon_72":"https:\/\/lh3.ggpht.com\/u1O7tcSzw3BbbUtnoNMGtYDcjYaw9ZqMafBeRs6M6G4n1rTVLE1xEdab-JW33RJuWQ=w72","promo_video":"","market_url":"https:\/\/play.google.com\/store\/apps\/details?id=com.stitcher.app&referrer=utm_source%3D42matters.com%26utm_medium%3Dapi","deep_link":"http:\/\/playboard.me\/android\/apps\/com.stitcher.app"}