{"package_name":"com.smartphonemate.smglobal","title":"SmartPhoneMate","description":"Welcome to the smartphonemate family! We are a research firm studying smart phone industry. We try to understand and study how people use their phones. Our research tool is this application called SmartPhoneMate that participants install on their phone. More than 50,000 people have downloaded this application across all platforms and still growing everyday! All one needs to do is to download, register and keep the application active. You will also be eligible for awards when joining the study. Our research is based on voluntary participation and you can opt out anytime you like by removing the application.\n\nPlease visit our website www.smartphonemate.mobi for terms and conditions, privacy policy and FAQ. The app collects data related to the usage of your device and does not collect any personal information like usernames, passwords or other secure information. \n\nFor support or question, write to support@smartphonemate.com\n\n\n\n\n\n","short_desc":"Welcome to the SmartPhoneMate family","rating":4.2035512924194,"category":"Entertainment","cat_int":7,"cat_type":0,"cat_key":"ENTERTAINMENT","cat_keys":["ENTERTAINMENT","APPLICATION"],"price":"","price_numeric":0,"iap":false,"iap_min":0,"iap_max":0,"size":3355443,"downloads":"100,000 - 500,000","downloads_min":100000,"downloads_max":500000,"version":"SmartPhoneMate_3.0.2","content_rating":"Everyone","what_is_new":"Playstore Policy Update.\n","market_update":"2016-06-03T00:00:00+00:00","screenshots":["https:\/\/lh4.ggpht.com\/lv6B0MM0WOLAOLE6KJTBlrX6DpTmh8ztMVgkBkDZpNFfjDUq8T1aLSOcJNNQJNIfyB8=h310","https:\/\/lh3.ggpht.com\/2ctzD-XnCdqAaq9AqI5kUFafCJN_XdgtkbIsQUTWXkRZmAA5xkVoU8arvg-qFdmGnzY=h310"],"lang":"en","i18n_lang":["en"],"price_i18n_countries":[],"website":"http:\/\/smartphonemate.mobi\/","from_developer":["com.imi.simmonsconnect","com.informate.datadiary"],"created":"2016-06-03T00:00:00+00:00","developer":"Informate Mobile Intelligence","number_ratings":6082,"icon":"https:\/\/lh5.ggpht.com\/YP9oEysGnC45Sj3vaw40wAzfQbUWJRlUISOnPhpgdONZNlQlw0K9XFQpuBRrbiN6Ya8=w300","icon_72":"https:\/\/lh5.ggpht.com\/YP9oEysGnC45Sj3vaw40wAzfQbUWJRlUISOnPhpgdONZNlQlw0K9XFQpuBRrbiN6Ya8=w72","promo_video":"","market_url":"https:\/\/play.google.com\/store\/apps\/details?id=com.smartphonemate.smglobal&referrer=utm_source%3D42matters.com%26utm_medium%3Dapi","deep_link":"http:\/\/playboard.me\/android\/apps\/com.smartphonemate.smglobal"}